data/entry1.txt
data/entry2.txt
data/template.html
gresiblos/__init__.py
gresiblos/gresiblos.py
gresiblos-0.6.0.dist-info/licenses/LICENSE
tests/cfg1.cfg
tests/cfg2.cfg
tests/entries_sum.json
tests/entries_sum_php.json
tests/entry1_sum.json
tests/entry1_sum_php.json
tests/entry2_sum.json
tests/my-first-blog-entry.html
tests/my-first-blog-entry_phpindex.html
tests/my-second-blog-entry.html
tests/test_main.py
tests/test_main_config.py
tests/test_main_examples.py
tests/test_main_index_indent.py
tests/test_main_lists.py
tests/test_main_opt_modules.py
tests/test_opt_doc_part.py
tests/test_replacement.py
tests/test_topic_encoding.py
tests/util.py
tools/feed.php
tools/index.php
gresiblos-0.6.0.dist-info/METADATA
gresiblos-0.6.0.dist-info/WHEEL
gresiblos-0.6.0.dist-info/entry_points.txt
gresiblos-0.6.0.dist-info/top_level.txt
gresiblos-0.6.0.dist-info/RECORD
