Metadata-Version: 2.4
Name: gresiblos
Version: 0.6.0
Summary: A simple private blogging system
Home-page: http://gresiblos.readthedocs.org/
Download-URL: http://pypi.python.org/pypi/gresiblos
Author: dkrajzew
Author-email: d.krajzewicz@gmail.com
License: BSD-3-Clause
Project-URL: Documentation, https://gresiblos.readthedocs.io/
Project-URL: Source, https://github.com/dkrajzew/gresiblos
Project-URL: Tracker, https://github.com/dkrajzew/gresiblos/issues
Project-URL: Discussions, https://github.com/dkrajzew/gresiblos/discussions
Classifier: Development Status :: 4 - Beta
Classifier: Environment :: Console
Classifier: Programming Language :: Python
Classifier: Programming Language :: Python :: 3
Classifier: Operating System :: OS Independent
Classifier: Intended Audience :: Developers
Classifier: Intended Audience :: Information Technology
Classifier: Intended Audience :: Telecommunications Industry
Classifier: Intended Audience :: Other Audience
Classifier: Topic :: Communications
Classifier: Topic :: Documentation
Classifier: Topic :: Internet
Classifier: Topic :: Internet :: WWW/HTTP :: Dynamic Content
Classifier: Topic :: Text Processing
Requires-Python: >=3, <4
License-File: LICENSE
Dynamic: author
Dynamic: author-email
Dynamic: classifier
Dynamic: description
Dynamic: description-content-type
Dynamic: download-url
Dynamic: home-page
Dynamic: license
Dynamic: license-file
Dynamic: project-url
Dynamic: requires-python
Dynamic: summary
